plonegovbr/brfields/__init__.py
plonegovbr/brfields/configure.zcml
plonegovbr/brfields/dependencies.zcml
plonegovbr/brfields/interfaces.py
plonegovbr/brfields/profiles.zcml
plonegovbr/brfields/testing.py
plonegovbr/brfields/content/__init__.py
plonegovbr/brfields/content/demo.py
plonegovbr/brfields/fields/__init__.py
plonegovbr/brfields/fields/cep.py
plonegovbr/brfields/fields/cnpj.py
plonegovbr/brfields/fields/cpf.py
plonegovbr/brfields/fields/estados.py
plonegovbr/brfields/fields/fone.py
plonegovbr/brfields/indexers/__init__.py
plonegovbr/brfields/indexers/configure.zcml
plonegovbr/brfields/locales/__init__.py
plonegovbr/brfields/locales/__main__.py
plonegovbr/brfields/locales/plonegovbr.brfields.pot
plonegovbr/brfields/locales/en/LC_MESSAGES/plonegovbr.brfields.mo
plonegovbr/brfields/locales/en/LC_MESSAGES/plonegovbr.brfields.po
plonegovbr/brfields/locales/pt_BR/LC_MESSAGES/plonegovbr.brfields.mo
plonegovbr/brfields/locales/pt_BR/LC_MESSAGES/plonegovbr.brfields.po
plonegovbr/brfields/profiles/default/browserlayer.xml
plonegovbr/brfields/profiles/default/metadata.xml
plonegovbr/brfields/profiles/default/types.xml
plonegovbr/brfields/profiles/demo/metadata.xml
plonegovbr/brfields/profiles/demo/theme.xml
plonegovbr/brfields/profiles/demo/types.xml
plonegovbr/brfields/profiles/demo/registry/plone.base.interfaces.controlpanel.INavigationSchema.xml
plonegovbr/brfields/profiles/demo/types/.gitkeep
plonegovbr/brfields/profiles/demo/types/DemoContent.xml
plonegovbr/brfields/profiles/uninstall/browserlayer.xml
plonegovbr/brfields/serializers/__init__.py
plonegovbr/brfields/serializers/configure.zcml
plonegovbr/brfields/serializers/fields.py
plonegovbr/brfields/setuphandlers/__init__.py
plonegovbr/brfields/setuphandlers/initial.py
plonegovbr/brfields/setuphandlers/examplecontent/.gitkeep
plonegovbr/brfields/setuphandlers/examplecontent/content/__metadata__.json
plonegovbr/brfields/setuphandlers/examplecontent/content/1440d5aaaeb24c27933788929410f76f/data.json
plonegovbr.brfields-1.0.0a3.dist-info/METADATA
plonegovbr.brfields-1.0.0a3.dist-info/WHEEL
plonegovbr.brfields-1.0.0a3.dist-info/entry_points.txt
plonegovbr.brfields-1.0.0a3.dist-info/licenses/LICENSE.GPL
plonegovbr.brfields-1.0.0a3.dist-info/licenses/LICENSE.md
plonegovbr.brfields-1.0.0a3.dist-info/RECORD
