Metadata-Version: 2.4
Name: plonegovbr.brfields
Version: 1.0.0a3
Summary: Packages implementing fields used in Brazil for Dexterity and Volto projects
Project-URL: Homepage, https://github.com/plonegovbr/brfieldsandwidgets
Project-URL: PyPI, https://pypi.org/project/plonegovbr.brfields
Project-URL: Source, https://github.com/plonegovbr/brfieldsandwidgets
Project-URL: Tracker, https://github.com/plonegovbr/brfieldsandwidgets/issues
Author-email: PloneGov-BR <gov@plone.org.br>
License-Expression: GPL-2.0-only
License-File: LICENSE.GPL
License-File: LICENSE.md
Keywords: CMS,Dexterity,Plone,Python,eGov
Classifier: Development Status :: 3 - Alpha
Classifier: Environment :: Web Environment
Classifier: Framework :: Plone
Classifier: Framework :: Plone :: 6.0
Classifier: Framework :: Plone :: 6.1
Classifier: Framework :: Plone :: Addon
Classifier: License :: OSI Approved :: GNU General Public License v2 (GPLv2)
Classifier: Operating System :: OS Independent
Classifier: Programming Language :: Python
Classifier: Programming Language :: Python :: 3.10
Classifier: Programming Language :: Python :: 3.11
Classifier: Programming Language :: Python :: 3.12
Classifier: Programming Language :: Python :: 3.13
Requires-Python: >=3.10
Requires-Dist: plone-api
Requires-Dist: plone-restapi
Requires-Dist: plone-volto
Requires-Dist: products-cmfplone>=6.0
Requires-Dist: validate-docbr>=1.10.0
Provides-Extra: test
Requires-Dist: plone-app-testing; extra == 'test'
Requires-Dist: plone-exportimport; extra == 'test'
Requires-Dist: plone-restapi[test]; extra == 'test'
Requires-Dist: pytest; extra == 'test'
Requires-Dist: pytest-cov; extra == 'test'
Requires-Dist: pytest-plone>=0.5.0; extra == 'test'
Requires-Dist: zest-releaser[recommended]; extra == 'test'
Requires-Dist: zestreleaser-towncrier; extra == 'test'
